ggallery/__init__.py
ggallery/__main__.py
ggallery/config.py
ggallery/gallery_generator.py
ggallery/model.py
ggallery/docker/Dockerfile
ggallery/docker/__init__.py
ggallery/docker/docker_image_builder.py
ggallery/docker/nginx.conf
ggallery/favicon/__init__.py
ggallery/favicon/base_favicon_provider.py
ggallery/favicon/fontawesome_favicon_provider.py
ggallery/favicon/local_favicon_provider.py
ggallery/image/__init__.py
ggallery/image/thumbnail_creator.py
ggallery/renderers/__init__.py
ggallery/renderers/base_renderer.py
ggallery/renderers/import_renderer.py
ggallery/storage/__init__.py
ggallery/storage/azure_blob_storage.py
ggallery/storage/base_provider.py
ggallery/storage/local_storage.py
ggallery-1.1.3.dist-info/licenses/LICENSE
tests/__init__.py
tests/conftest.py
tests/gallery_config_factory.py
tests/test_gallery_generator.py
ggallery-1.1.3.dist-info/METADATA
ggallery-1.1.3.dist-info/WHEEL
ggallery-1.1.3.dist-info/entry_points.txt
ggallery-1.1.3.dist-info/top_level.txt
ggallery-1.1.3.dist-info/RECORD
