Metadata-Version: 2.4
Name: ggallery
Version: 1.1.3
Summary: A tool to generate static HTML photo galleries from various data sources.
Author-email: Radzivon Chorny <mityy2012@gmail.com>
Project-URL: Documentation, https://github.com/creeston/ggallery
Project-URL: Source, https://github.com/creeston/ggallery
Project-URL: Tracker, https://github.com/creeston/ggallery/issues
Keywords: static,html,photo,gallery,generator
Classifier: Programming Language :: Python :: 3
Classifier: Operating System :: OS Independent
Requires-Python: >=3.11
License-File: LICENSE
Requires-Dist: azure-storage-blob>=12.26.0
Requires-Dist: docker>=7.1.0
Requires-Dist: dotenv>=0.9.9
Requires-Dist: pillow>=11.3.0
Requires-Dist: pydantic>=2.11.7
Requires-Dist: pytest>=8.4.1
Requires-Dist: pyyaml>=6.0.2
Requires-Dist: ruff>=0.12.5
Requires-Dist: setuptools>=80.9.0
Requires-Dist: testcontainers[azurite]>=4.12.0
Dynamic: license-file
